{"cameraMode":{"drawMode":0,"name":"Shaded","section":"Shading Mode"},"sceneLighting":false,"audioPlay":false,"sceneViewState":{"showFog":true,"showMaterialUpdate":false,"showSkybox":false,"showFlares":true,"showImageEffects":true,"showParticleSystems":true},"in2DMode":false,"pivot":{"x":4.064969539642334,"y":4.688412666320801,"z":-2.8229503631591799},"rotation":{"x":0.007813391275703907,"y":-0.05558611825108528,"z":0.0001553496695123613,"w":0.9985040426254273},"size":19.2470645904541,"orthographic":false}